LICENSE.txt
README.md
setup.cfg
setup.py
lifelike/__init__.py
lifelike/brain.py
lifelike/state.py
lifelike.egg-info/PKG-INFO
lifelike.egg-info/SOURCES.txt
lifelike.egg-info/dependency_links.txt
lifelike.egg-info/requires.txt
lifelike.egg-info/top_level.txt
lifelike/StateManager/__init__.py
lifelike/StateManager/base_game_tree.py
lifelike/StateManager/knowledge_tree.py
lifelike/StateManager/sequence_tree.py