Metadata-Version: 2.1
Name: lifelike
Version: 1.0.7
Summary: A A toolkit that allows for the creation of "lifelike" characters that you can interact with and change how they behave towards you
Author: Mustafa Tariq and Khoa Nguyen
License: MIT
License-File: LICENSE.txt
